{
"id":"1020",
"name":"海藻保湿面膜",
"pcode":"",
"price":320,
"desc":"<br />富含海藻和金盏花的温和面膜，可舒缓镇定肌肤，给予肌肤 水润滋养。成分中的绿茶萃取精华和维他命E，具有极佳抗氧化效果， 能改善肌肤因缺水而造成的暗沉。",
"ingredient":"<br />金盏花油<br />金盏花油是从万寿菊科鲜花中萃取的一种精油。 其性质柔和，适合所有油性肌肤，包括敏感性肌肤使用。 金盏花油可舒缓肌肤，尤其是敏感性肌肤。<br />甘油<br />甘油是肥皂生产过程中产生的副产品，是一种清澈、类似糖浆的液体，通常由植物油衍生而来，通过向脂肪和固体油中添加碱性成分而获得。 甘油在许多护肤产品中用作可溶性保湿剂和润滑剂，由于它会吸收空气中的水分，因此有助于保留产品中的水分。 它使产品更易涂抹，有明显的保湿效果。",
"guide":"<br />适合干性、中偏干和中性肌肤特别适合。<br />取足量，以向上画圈的动作，涂抹于刚清洁后带湿气的脸上，避开眼周。让面膜在脸上停留10-15分钟 。以温水和湿毛巾清除洗净。<br />海藻保湿面膜可以在任何需要时候使用，或者一周使用一至三次。",
"giftid":"",
"color":"",
"capacity":"",
"efficacy":"",
"commentid":"",
"recommend":"",
"offer":"",
"products":[],
"imgs":"/handy/upload/images/goods/20131010/67/201310101405070_main_S.jpg"
}
