{
"id":"1031",
"name":"粉柚香水",
"pcode":"",
"price":450,
"desc":"<br />以两种独特的关键成分为主，采用传统的芳香采集方法，不破坏当地环境且令其能持久开采，成份比普通香水更天然",
"ingredient":"<br />西洋梨（西洋梨果提取物）<br />来源:西洋梨产自日本东京的传统果园。<br />芳香采集方法:由于西洋梨的花瓣的脆弱性质，科颜氏对其它天然成分采取特殊提取方法，以复制西洋梨独有的香味品质 - 柔和、花香、清新。<br />柚果（柚果提取物）<br />来源:产自巴西的具有提神效果的甜美多汁柑橘类水果。<br />芳香采集方法:柚的皮和果肉具有迥然不同的香味品质 - 苦涩与清新。科颜氏将两者融合在一起，开发出了独特的柚香味组合。",
"guide":"<br />我们建议您使用完整的一套沐浴啫哩、润肤乳、香氛，这样能令您喜爱的香氛余味持久，带给您一整天的好心情。",
"giftid":"",
"color":"",
"capacity":"",
"efficacy":"",
"commentid":"",
"recommend":"",
"offer":"",
"products":[],
"imgs":"/handy/upload/images/goods/20131010/67/201310101416520_main_B.jpg"
}
